hdc_py/__init__.py
hdc_py/hdc.py
hdc_py-0.1.3.dist-info/licenses/LICENSE
hdc_py-0.1.3.dist-info/WHEEL
hdc_py-0.1.3.dist-info/METADATA
hdc_py-0.1.3.dist-info/RECORD
