Metadata-Version: 2.4
Name: hdc-py
Version: 0.1.3
Summary: A python wrapper around the (Open-) Harmony device connector
License-Expression: Apache-2.0
License-File: LICENSE
Classifier: Programming Language :: Python :: 3
Classifier: Operating System :: OS Independent
Requires-Python: >=3.11
Project-URL: Homepage, https://github.com/openharmony-rs/hdc-py
Project-URL: Issues, https://github.com/openharmony-rs/hdc-py/issues
